dlt_with_debug/__init__.py
dlt_with_debug/dlt_signatures.py
dlt_with_debug/helpers.py
dlt_with_debug/v2.py
dlt_with_debug-2.2.dist-info/LICENSE
dlt_with_debug-2.2.dist-info/METADATA
dlt_with_debug-2.2.dist-info/WHEEL
dlt_with_debug-2.2.dist-info/top_level.txt
dlt_with_debug-2.2.dist-info/RECORD
