Metadata-Version: 2.1
Name: dlt_with_debug
Version: 2.2
Summary: Utility for running workflows leveraging delta live tables from interactive notebooks
Home-page: https://github.com/souvik-databricks/dlt-with-debug
Author: Souvik Pratiher
Author-email: souvik.pratiher@databricks.com
Keywords: python3,delta live tables
Classifier: Development Status :: 5 - Production/Stable
Classifier: Intended Audience :: Developers
Classifier: Programming Language :: Python :: 3
License-File: LICENSE
